d4rl/__init__.py
d4rl/infos.py
d4rl/offline_env.py
d4rl/ope.py
d4rl/carla/__init__.py
d4rl/carla/carla_env.py
d4rl/carla/data_collection_agent_lane.py
d4rl/carla/data_collection_town.py
d4rl/carla/town_agent.py
d4rl/flow/__init__.py
d4rl/flow/bottleneck.py
d4rl/flow/merge.py
d4rl/flow/traffic_light_grid.py
d4rl/gym_bullet/__init__.py
d4rl/gym_bullet/gym_envs.py
d4rl/gym_minigrid/__init__.py
d4rl/gym_minigrid/fourroom_controller.py
d4rl/gym_minigrid/minigrid.py
d4rl/gym_minigrid/register.py
d4rl/gym_minigrid/rendering.py
d4rl/gym_minigrid/roomgrid.py
d4rl/gym_minigrid/window.py
d4rl/gym_minigrid/wrappers.py
d4rl/gym_minigrid/envs/__init__.py
d4rl/gym_minigrid/envs/empty.py
d4rl/gym_minigrid/envs/fourrooms.py
d4rl/gym_mujoco/__init__.py
d4rl/gym_mujoco/gym_envs.py
d4rl/hand_manipulation_suite/__init__.py
d4rl/hand_manipulation_suite/door_v0.py
d4rl/hand_manipulation_suite/hammer_v0.py
d4rl/hand_manipulation_suite/pen_v0.py
d4rl/hand_manipulation_suite/relocate_v0.py
d4rl/hand_manipulation_suite/Adroit/Adroit_hand.xml
d4rl/hand_manipulation_suite/Adroit/Adroit_hand_withOverlay.xml
d4rl/hand_manipulation_suite/Adroit/LICENSE
d4rl/hand_manipulation_suite/Adroit/README.md
d4rl/hand_manipulation_suite/Adroit/gallery/news.JPG
d4rl/hand_manipulation_suite/Adroit/gallery/projects.JPG
d4rl/hand_manipulation_suite/Adroit/resources/assets.xml
d4rl/hand_manipulation_suite/Adroit/resources/chain.xml
d4rl/hand_manipulation_suite/Adroit/resources/chain1.xml
d4rl/hand_manipulation_suite/Adroit/resources/joint_position_actuation.xml
d4rl/hand_manipulation_suite/Adroit/resources/tendon_torque_actuation.xml
d4rl/hand_manipulation_suite/Adroit/resources/meshes/F1.stl
d4rl/hand_manipulation_suite/Adroit/resources/meshes/F2.stl
d4rl/hand_manipulation_suite/Adroit/resources/meshes/F3.stl
d4rl/hand_manipulation_suite/Adroit/resources/meshes/TH1_z.stl
d4rl/hand_manipulation_suite/Adroit/resources/meshes/TH2_z.stl
d4rl/hand_manipulation_suite/Adroit/resources/meshes/TH3_z.stl
d4rl-1.1.dist-info/LICENSE
d4rl-1.1.dist-info/METADATA
d4rl-1.1.dist-info/WHEEL
d4rl-1.1.dist-info/top_level.txt
d4rl-1.1.dist-info/RECORD
