Metadata-Version: 2.1
Name: d4rl
Version: 1.1
License-File: LICENSE
Requires-Dist: gym (<0.25.0)
Requires-Dist: numpy
Requires-Dist: mujoco-py
Requires-Dist: pybullet
Requires-Dist: h5py
Requires-Dist: termcolor
Requires-Dist: click
Requires-Dist: dm-control (>=1.0.3)
